Metadata-Version: 2.3
Name: e2b
Version: 2.12.2
Summary: E2B SDK that give agents cloud environments
License: MIT
Author: e2b
Author-email: hello@e2b.dev
Requires-Python: >=3.10,<4.0
Classifier: License :: OSI Approved :: MIT License
Classifier: Programming Language :: Python :: 3
Classifier: Programming Language :: Python :: 3.10
Classifier: Programming Language :: Python :: 3.11
Classifier: Programming Language :: Python :: 3.12
Classifier: Programming Language :: Python :: 3.13
Requires-Dist: attrs (>=23.2.0)
Requires-Dist: dockerfile-parse (>=2.0.1,<3.0.0)
Requires-Dist: httpcore (>=1.0.5,<2.0.0)
Requires-Dist: httpx (>=0.27.0,<1.0.0)
Requires-Dist: packaging (>=24.1)
Requires-Dist: protobuf (>=4.21.0)
Requires-Dist: python-dateutil (>=2.8.2)
Requires-Dist: rich (>=14.0.0)
Requires-Dist: typing-extensions (>=4.1.0)
Requires-Dist: wcmatch (>=10.1,<11.0)
Project-URL: Bug Tracker, https://github.com/e2b-dev/e2b/issues
Project-URL: Homepage, https://e2b.dev/
Project-URL: Repository, https://github.com/e2b-dev/e2b/tree/main/packages/python-sdk
